sequences/__init__.py
sequences-0.0.8.dist-info/LICENSE.txt
sequences-0.0.8.dist-info/METADATA
sequences-0.0.8.dist-info/WHEEL
sequences-0.0.8.dist-info/top_level.txt
sequences-0.0.8.dist-info/RECORD
