Metadata-Version: 2.1
Name: sequences
Version: 0.0.8
Summary: provides the most famous of sequences of the OEIS
Home-page: https://github.com/divyajeettt/sequences
Author: Divyajeet Singh
Author-email: knightt1821@gmail.com
Classifier: Programming Language :: Python :: 3
Classifier: License :: OSI Approved :: MIT License
Classifier: Operating System :: OS Independent
License-File: LICENSE.txt
